htmlBuilder/__init__.py
htmlBuilder/attributes.py
htmlBuilder/exceptions.py
htmlBuilder/tags.py
htmlBuilder/test.py
htmlBuilder/utils.py
htmlBuilder-1.0.0.dist-info/LICENSE.txt
htmlBuilder-1.0.0.dist-info/METADATA
htmlBuilder-1.0.0.dist-info/WHEEL
htmlBuilder-1.0.0.dist-info/top_level.txt
htmlBuilder-1.0.0.dist-info/RECORD
