Metadata-Version: 2.1
Name: htmlBuilder
Version: 1.0.0
Summary: A beautiful html builder library.
Home-page: https://github.com/jaimevp54/htmlBuilder
Author: Jaime Viñas
Author-email: jaimevp54@gmail.com
License: MIT
Download-URL: https://github.com/jaimevp54/htmlBuilder/archive/1.0.0.tar.gz
Keywords: html,builder,render,template,templating,python
Platform: UNKNOWN
Classifier: Intended Audience :: Developers
Classifier: License :: OSI Approved :: MIT License
Classifier: Operating System :: OS Independent
Classifier: Programming Language :: Python :: 3.6
Classifier: Programming Language :: Python :: 3.7
Classifier: Programming Language :: Python :: 3.8
Classifier: Programming Language :: Python :: 3.9
Classifier: Topic :: Internet :: WWW/HTTP :: Dynamic Content
Classifier: Topic :: Software Development :: Libraries :: Python Modules
Classifier: Topic :: Text Processing :: Markup :: HTML
Requires-Python: >=3.6
